confluence_content_parser/__init__.py
confluence_content_parser/document.py
confluence_content_parser/nodes.py
confluence_content_parser/parser.py
confluence_content_parser/py.typed
confluence_content_parser-0.2.1.dist-info/WHEEL
confluence_content_parser-0.2.1.dist-info/METADATA
confluence_content_parser-0.2.1.dist-info/RECORD
