Metadata-Version: 2.3
Name: confluence-content-parser
Version: 0.2.1
Summary: A Python library for parsing Confluence Storage Format content into structured data
Keywords: confluence,parser,xml,content
Author: Uladzislau Hubar
Author-email: Uladzislau Hubar <hubar.uladzislau@gmail.com>
Classifier: Development Status :: 3 - Alpha
Classifier: Intended Audience :: Developers
Classifier: License :: OSI Approved :: Apache Software License
Classifier: Programming Language :: Python :: 3
Classifier: Programming Language :: Python :: 3.12
Classifier: Topic :: Text Processing :: Markup :: XML
Classifier: Topic :: Software Development :: Libraries :: Python Modules
Requires-Dist: lxml>=6.0.1
Requires-Dist: pydantic>=2.11.7
Requires-Dist: types-lxml>=2025.8.25
Requires-Python: >=3.12
Provides-Extra: dev
